nosemouse/__init__.py
nosemouse/__main__.py
nosemouse/head.py
nosemouse/facial_landmark_detection/LICENCE
nosemouse/facial_landmark_detection/__init__.py
nosemouse/facial_landmark_detection/face_detector.py
nosemouse/facial_landmark_detection/facial_landmark_detector.py
nosemouse/gaze_detection/LICENSE
nosemouse/gaze_detection/__init__.py
nosemouse/gaze_detection/calibration.py
nosemouse/gaze_detection/eye.py
nosemouse/gaze_detection/gaze_tracking.py
nosemouse/gaze_detection/pupil.py
nosemouse/models/face_model/README.md
nosemouse/models/facial_landmark_model/README.md
nosemouse/models/gaze_model/README.md
nosemouse-0.0.2.dist-info/LICENSE
nosemouse-0.0.2.dist-info/WHEEL
nosemouse-0.0.2.dist-info/METADATA
nosemouse-0.0.2.dist-info/RECORD
