Metadata-Version: 2.1
Name: nosemouse
Version: 0.0.2
Summary: nosemouse - move mouse with your nose
Home-page: https://github.com/ollipal/nosemouse
License: UNKNOWN
Author: Olli Paloviita
Author-email: olli.paloviita@gmail.com
Classifier: License :: OSI Approved :: GNU General Public License v3 or later (GPLv3+)
Requires-Dist: tensorflow ==2.2
Requires-Dist: scikit-learn
Requires-Dist: numpy
Requires-Dist: opencv_contrib_python
Requires-Dist: dlib ==19.16.0
Requires-Dist: keyboard
Requires-Dist: mouse
Requires-Dist: screeninfo
